poseigen_trident/preass.py
poseigen_trident/prongs.py
poseigen_trident/utils.py
poseigen_trident-0.0.1.dist-info/LICENSE.txt
poseigen_trident-0.0.1.dist-info/METADATA
poseigen_trident-0.0.1.dist-info/WHEEL
poseigen_trident-0.0.1.dist-info/RECORD
